<entryForm scriptid="custform_br_delivered_costs" standard="STANDARDCUSTOMRECORD_BR_DELIVERED_COSTSFORM">
  <name>BR Delivered Costs Form</name>
  <recordType>[scriptid=customrecord_br_delivered_costs]</recordType>
  <inactive>F</inactive>
  <preferred>T</preferred>
  <storedWithRecord>F</storedWithRecord>
  <mainFields>
    <defaultFieldGroup>
      <fields position="MIDDLE">
        <field>
          <id>CUSTOMFORM</id>
          <label>Custom Form</label>
          <visible>T</visible>
          <mandatory>T</mandatory>
          <displayType>NORMAL</displayType>
          <columnBreak>F</columnBreak>
          <sameRowAsPrevious>F</sameRowAsPrevious>
          <quickAdd>F</quickAdd>
        </field>
        <field>
          <id>NAME</id>
          <label>Name</label>
          <visible>T</visible>
          <mandatory>T</mandatory>
          <displayType>NORMAL</displayType>
          <columnBreak>F</columnBreak>
          <sameRowAsPrevious>F</sameRowAsPrevious>
          <quickAdd>T</quickAdd>
        </field>
        <field>
          <id>[scriptid=customrecord_br_delivered_costs.custrecord_br_delvd_shipping_weight]</id>
          <label>Shipping Weight</label>
          <visible>T</visible>
          <mandatory>T</mandatory>
          <displayType>NORMAL</displayType>
          <columnBreak>F</columnBreak>
          <sameRowAsPrevious>F</sameRowAsPrevious>
          <quickAdd>F</quickAdd>
        </field>
        <field>
          <id>ISINACTIVE</id>
          <label>Inactive</label>
          <visible>T</visible>
          <mandatory>F</mandatory>
          <displayType>NORMAL</displayType>
          <columnBreak>F</columnBreak>
          <sameRowAsPrevious>F</sameRowAsPrevious>
          <quickAdd>F</quickAdd>
        </field>
        <field>
          <id>[scriptid=customrecord_br_delivered_costs.custrecord_br_delvd_cost_defaults]</id>
          <label>Item Costing Defaults</label>
          <visible>T</visible>
          <mandatory>F</mandatory>
          <displayType>NORMAL</displayType>
          <columnBreak>T</columnBreak>
          <sameRowAsPrevious>F</sameRowAsPrevious>
          <quickAdd>F</quickAdd>
        </field>
        <field>
          <id>[scriptid=customrecord_br_delivered_costs.custrecord_br_delvd_memo]</id>
          <label>Memo</label>
          <visible>T</visible>
          <mandatory>F</mandatory>
          <displayType>NORMAL</displayType>
          <columnBreak>F</columnBreak>
          <sameRowAsPrevious>F</sameRowAsPrevious>
          <quickAdd>F</quickAdd>
        </field>
        <field>
          <id>RECORDID</id>
          <label>ID</label>
          <visible>T</visible>
          <mandatory>T</mandatory>
          <displayType>NORMAL</displayType>
          <columnBreak>F</columnBreak>
          <sameRowAsPrevious>F</sameRowAsPrevious>
          <quickAdd>F</quickAdd>
        </field>
        <field>
          <id>OWNER</id>
          <label>Owner</label>
          <visible>F</visible>
          <mandatory>T</mandatory>
          <displayType>NORMAL</displayType>
          <columnBreak>F</columnBreak>
          <sameRowAsPrevious>F</sameRowAsPrevious>
          <quickAdd>F</quickAdd>
        </field>
        <field>
          <id>CREATED</id>
          <label>Date Created</label>
          <visible>F</visible>
          <mandatory>T</mandatory>
          <displayType>NORMAL</displayType>
          <columnBreak>F</columnBreak>
          <sameRowAsPrevious>F</sameRowAsPrevious>
          <quickAdd>F</quickAdd>
        </field>
        <field>
          <id>LASTMODIFIED</id>
          <label>Last Modified</label>
          <visible>F</visible>
          <mandatory>T</mandatory>
          <displayType>NORMAL</displayType>
          <columnBreak>F</columnBreak>
          <sameRowAsPrevious>F</sameRowAsPrevious>
          <quickAdd>F</quickAdd>
        </field>
        <field>
          <id>PARENT</id>
          <label>Parent</label>
          <visible>F</visible>
          <mandatory>F</mandatory>
          <displayType>NORMAL</displayType>
          <columnBreak>F</columnBreak>
          <sameRowAsPrevious>F</sameRowAsPrevious>
          <quickAdd>F</quickAdd>
        </field>
      </fields>
    </defaultFieldGroup>
  </mainFields>
  <tabs>
    <tab>
      <id>[scriptid=customrecord_br_delivered_costs.tab_409_4311009_sb1_310]</id>
      <label>FBM</label>
      <visible>T</visible>
      <fieldGroups>
        <fieldGroup scriptid="fieldgroup_2_4311009_sb1_178">
          <label>Defaults</label>
          <visible>T</visible>
          <showTitle>T</showTitle>
          <singleColumn>F</singleColumn>
          <fields position="MIDDLE">
            <field>
              <id>[scriptid=customrecord_br_delivered_costs.custrecord_br_delvd_residential_pct]</id>
              <label>Residential Delivery %</label>
              <visible>T</visible>
              <mandatory>F</mandatory>
              <displayType>NORMAL</displayType>
              <columnBreak>F</columnBreak>
              <sameRowAsPrevious>F</sameRowAsPrevious>
              <quickAdd>F</quickAdd>
            </field>
            <field>
              <id>[scriptid=customrecord_br_delivered_costs.custrecord_br_delvd_peak_surc_total_fbm]</id>
              <label>Total Peak Surcharge</label>
              <visible>T</visible>
              <mandatory>F</mandatory>
              <displayType>NORMAL</displayType>
              <columnBreak>T</columnBreak>
              <sameRowAsPrevious>F</sameRowAsPrevious>
              <quickAdd>F</quickAdd>
            </field>
            <field>
              <id>[scriptid=customrecord_br_delivered_costs.custrecord_br_delvd_peaksurchg_std_fbm]</id>
              <label>Peak Surcharge - Standard</label>
              <visible>T</visible>
              <mandatory>F</mandatory>
              <displayType>NORMAL</displayType>
              <columnBreak>F</columnBreak>
              <sameRowAsPrevious>F</sameRowAsPrevious>
              <quickAdd>F</quickAdd>
            </field>
            <field>
              <id>[scriptid=customrecord_br_delivered_costs.custrecord_br_delvd_peaksurchg_hol_fbm]</id>
              <label>Peak Surcharge - Holiday</label>
              <visible>T</visible>
              <mandatory>F</mandatory>
              <displayType>NORMAL</displayType>
              <columnBreak>F</columnBreak>
              <sameRowAsPrevious>F</sameRowAsPrevious>
              <quickAdd>F</quickAdd>
            </field>
            <field>
              <id>[scriptid=customrecord_br_delivered_costs.custrecord_br_delvd_area_surcharge]</id>
              <label>Delivery Area Surcharge</label>
              <visible>T</visible>
              <mandatory>F</mandatory>
              <displayType>NORMAL</displayType>
              <columnBreak>T</columnBreak>
              <sameRowAsPrevious>F</sameRowAsPrevious>
              <quickAdd>F</quickAdd>
            </field>
            <field>
              <id>[scriptid=customrecord_br_delivered_costs.custrecord_br_delvd_rem_area_surcharge]</id>
              <label>Remote Delivery Area Surcharge</label>
              <visible>T</visible>
              <mandatory>F</mandatory>
              <displayType>NORMAL</displayType>
              <columnBreak>F</columnBreak>
              <sameRowAsPrevious>F</sameRowAsPrevious>
              <quickAdd>F</quickAdd>
            </field>
            <field>
              <id>[scriptid=customrecord_br_delivered_costs.custrecord_br_delvd_other_surcharges]</id>
              <label>Other Surcharges</label>
              <visible>T</visible>
              <mandatory>F</mandatory>
              <displayType>NORMAL</displayType>
              <columnBreak>F</columnBreak>
              <sameRowAsPrevious>F</sameRowAsPrevious>
              <quickAdd>F</quickAdd>
            </field>
            <field>
              <id>[scriptid=customrecord_br_delivered_costs.custrecord_br_delvd_ups_discount_pct]</id>
              <label>UPS Fee Discount</label>
              <visible>T</visible>
              <mandatory>F</mandatory>
              <displayType>NORMAL</displayType>
              <columnBreak>T</columnBreak>
              <sameRowAsPrevious>F</sameRowAsPrevious>
              <quickAdd>F</quickAdd>
            </field>
          </fields>
        </fieldGroup>
        <fieldGroup scriptid="fieldgroup_3_4311009_sb1_637">
          <label>Costs</label>
          <visible>T</visible>
          <showTitle>T</showTitle>
          <singleColumn>F</singleColumn>
          <fields position="MIDDLE">
            <field>
              <id>[scriptid=customrecord_br_delivered_costs.custrecord_br_delvd_base_fbm]</id>
              <label>FBM Base Fee</label>
              <visible>T</visible>
              <mandatory>F</mandatory>
              <displayType>NORMAL</displayType>
              <columnBreak>F</columnBreak>
              <sameRowAsPrevious>F</sameRowAsPrevious>
              <quickAdd>F</quickAdd>
            </field>
            <field>
              <id>[scriptid=customrecord_br_delivered_costs.custrecord_br_delvd_residential_fbm]</id>
              <label>FBM Residential Fee</label>
              <visible>T</visible>
              <mandatory>F</mandatory>
              <displayType>NORMAL</displayType>
              <columnBreak>T</columnBreak>
              <sameRowAsPrevious>F</sameRowAsPrevious>
              <quickAdd>F</quickAdd>
            </field>
            <field>
              <id>[scriptid=customrecord_br_delivered_costs.custrecord_br_delvd_overmaxlimit_fbm]</id>
              <label>FBM Over Max Limit Fee</label>
              <visible>T</visible>
              <mandatory>F</mandatory>
              <displayType>NORMAL</displayType>
              <columnBreak>F</columnBreak>
              <sameRowAsPrevious>F</sameRowAsPrevious>
              <quickAdd>F</quickAdd>
            </field>
            <field>
              <id>[scriptid=customrecord_br_delivered_costs.custrecord_br_delvd_peak_lgpkg_std_fbm]</id>
              <label>FBM Peak Surcharge Fee - Large Package</label>
              <visible>T</visible>
              <mandatory>F</mandatory>
              <displayType>NORMAL</displayType>
              <columnBreak>F</columnBreak>
              <sameRowAsPrevious>F</sameRowAsPrevious>
              <quickAdd>F</quickAdd>
            </field>
            <field>
              <id>[scriptid=customrecord_br_delivered_costs.custrecord_br_delvd_peak_addlhnd_std_fbm]</id>
              <label>FBM Peak Surcharge Fee - Add'l Handling</label>
              <visible>T</visible>
              <mandatory>F</mandatory>
              <displayType>NORMAL</displayType>
              <columnBreak>F</columnBreak>
              <sameRowAsPrevious>F</sameRowAsPrevious>
              <quickAdd>F</quickAdd>
            </field>
            <field>
              <id>[scriptid=customrecord_br_delivered_costs.custrecord_br_delvd_ah_weight_fbm]</id>
              <label>Additional Handling Fee: Weight</label>
              <visible>T</visible>
              <mandatory>F</mandatory>
              <displayType>NORMAL</displayType>
              <columnBreak>T</columnBreak>
              <sameRowAsPrevious>F</sameRowAsPrevious>
              <quickAdd>F</quickAdd>
            </field>
            <field>
              <id>[scriptid=customrecord_br_delivered_costs.custrecord_br_delvd_ah_len_girth_fbm]</id>
              <label>Additional Handling Fee: Length + Girth</label>
              <visible>T</visible>
              <mandatory>F</mandatory>
              <displayType>NORMAL</displayType>
              <columnBreak>F</columnBreak>
              <sameRowAsPrevious>F</sameRowAsPrevious>
              <quickAdd>F</quickAdd>
            </field>
            <field>
              <id>[scriptid=customrecord_br_delivered_costs.custrecord_br_delvd_ah_length_fbm]</id>
              <label>Additional Handling Fee: Length</label>
              <visible>T</visible>
              <mandatory>F</mandatory>
              <displayType>NORMAL</displayType>
              <columnBreak>F</columnBreak>
              <sameRowAsPrevious>F</sameRowAsPrevious>
              <quickAdd>F</quickAdd>
            </field>
            <field>
              <id>[scriptid=customrecord_br_delivered_costs.custrecord_br_delvd_ah_width_fbm]</id>
              <label>Additional Handling Fee: Width</label>
              <visible>T</visible>
              <mandatory>F</mandatory>
              <displayType>NORMAL</displayType>
              <columnBreak>F</columnBreak>
              <sameRowAsPrevious>F</sameRowAsPrevious>
              <quickAdd>F</quickAdd>
            </field>
            <field>
              <id>[scriptid=customrecord_br_delivered_costs.custrecord_br_delvd_ah_pkgng_fbm]</id>
              <label>Additional Handling Fee: Packaging</label>
              <visible>T</visible>
              <mandatory>F</mandatory>
              <displayType>NORMAL</displayType>
              <columnBreak>F</columnBreak>
              <sameRowAsPrevious>F</sameRowAsPrevious>
              <quickAdd>F</quickAdd>
            </field>
            <field>
              <id>[scriptid=customrecord_br_delivered_costs.custrecord_br_delvd_res_len_girth_fbm]</id>
              <label> 	Large Package Fee: Residential Length + Girth</label>
              <visible>T</visible>
              <mandatory>F</mandatory>
              <displayType>NORMAL</displayType>
              <columnBreak>T</columnBreak>
              <sameRowAsPrevious>F</sameRowAsPrevious>
              <quickAdd>F</quickAdd>
            </field>
            <field>
              <id>[scriptid=customrecord_br_delivered_costs.custrecord_br_delvd_res_length_fbm]</id>
              <label>Large Package Fee: Residential Length</label>
              <visible>T</visible>
              <mandatory>F</mandatory>
              <displayType>NORMAL</displayType>
              <columnBreak>F</columnBreak>
              <sameRowAsPrevious>F</sameRowAsPrevious>
              <quickAdd>F</quickAdd>
            </field>
            <field>
              <id>[scriptid=customrecord_br_delivered_costs.custrecord_br_delvd_com_len_girth_fbm]</id>
              <label>Large Package Fee: Commercial Length + Girth</label>
              <visible>T</visible>
              <mandatory>F</mandatory>
              <displayType>NORMAL</displayType>
              <columnBreak>F</columnBreak>
              <sameRowAsPrevious>F</sameRowAsPrevious>
              <quickAdd>F</quickAdd>
            </field>
            <field>
              <id>[scriptid=customrecord_br_delivered_costs.custrecord_br_delvd_com_length_fbm]</id>
              <label>Large Package Fee: Commercial Length</label>
              <visible>T</visible>
              <mandatory>F</mandatory>
              <displayType>NORMAL</displayType>
              <columnBreak>F</columnBreak>
              <sameRowAsPrevious>F</sameRowAsPrevious>
              <quickAdd>F</quickAdd>
            </field>
          </fields>
        </fieldGroup>
        <fieldGroup scriptid="fieldgroup_4_4311009_sb1_296">
          <label>Instructions</label>
          <visible>T</visible>
          <showTitle>T</showTitle>
          <singleColumn>F</singleColumn>
          <fields position="MIDDLE">
            <field>
              <id>[scriptid=customrecord_br_delivered_costs.custrecord_fbm_instructions]</id>
              <label>FBM Instructions</label>
              <visible>T</visible>
              <mandatory>F</mandatory>
              <displayType>NORMAL</displayType>
              <columnBreak>F</columnBreak>
              <sameRowAsPrevious>F</sameRowAsPrevious>
              <quickAdd>F</quickAdd>
            </field>
          </fields>
        </fieldGroup>
        <defaultFieldGroup/>
      </fieldGroups>
      <subItems/>
    </tab>
    <tab>
      <id>[scriptid=customrecord_br_delivered_costs.tab_410_4311009_sb1_994]</id>
      <label>FBA</label>
      <visible>T</visible>
      <fieldGroups>
        <defaultFieldGroup/>
      </fieldGroups>
      <subItems/>
    </tab>
    <tab>
      <id>RECORDNOTES</id>
      <label>Notes</label>
      <visible>T</visible>
      <fieldGroups>
        <defaultFieldGroup/>
      </fieldGroups>
      <subItems>
        <subList>
          <id>RECORDUSERNOTES</id>
          <label>User Notes</label>
          <visible>T</visible>
          <neverEmpty>F</neverEmpty>
        </subList>
        <subList>
          <id>RECORDSYSTEMNOTES</id>
          <label>System Notes</label>
          <visible>T</visible>
          <neverEmpty>F</neverEmpty>
        </subList>
      </subItems>
    </tab>
    <tab>
      <id>RECORDMEDIA</id>
      <label>Files</label>
      <visible>T</visible>
      <fieldGroups>
        <defaultFieldGroup/>
      </fieldGroups>
      <subItems>
        <subList>
          <id>RECORDMEDIAITEM</id>
          <label>Files</label>
          <visible>T</visible>
          <neverEmpty>F</neverEmpty>
        </subList>
      </subItems>
    </tab>
    <tab>
      <id>RECORDWORKFLOW</id>
      <label>Workflow</label>
      <visible>T</visible>
      <fieldGroups>
        <defaultFieldGroup/>
      </fieldGroups>
      <subItems>
        <subList>
          <id>RECORDACTIVEWORKFLOWS</id>
          <label>Active Workflows</label>
          <visible>T</visible>
          <neverEmpty>F</neverEmpty>
        </subList>
        <subList>
          <id>RECORDWORKFLOWHISTORY</id>
          <label>Workflow History</label>
          <visible>T</visible>
          <neverEmpty>F</neverEmpty>
        </subList>
      </subItems>
    </tab>
    <tab>
      <id>RECORDCUSTOM</id>
      <label>Custom</label>
      <visible>T</visible>
      <fieldGroups>
        <defaultFieldGroup/>
      </fieldGroups>
      <subItems/>
    </tab>
  </tabs>
  <actionbar>
    <menu>
      <menuitem>
        <id>DELETE</id>
        <label>Delete</label>
        <visible>T</visible>
      </menuitem>
      <menuitem>
        <id>MAKECOPY</id>
        <label>Make Copy</label>
        <visible>T</visible>
      </menuitem>
      <menuitem>
        <id>NEW</id>
        <label>New</label>
        <visible>T</visible>
      </menuitem>
      <menuitem>
        <id>PRINT</id>
        <label>Print</label>
        <visible>T</visible>
      </menuitem>
      <menuitem>
        <id>SUBMITCOPY</id>
        <label>Save &amp; Copy</label>
        <visible>T</visible>
      </menuitem>
      <menuitem>
        <id>SUBMITNEW</id>
        <label>Save &amp; New</label>
        <visible>T</visible>
      </menuitem>
      <menuitem>
        <id>SUBMITNEXT</id>
        <label>Save &amp; Next</label>
        <visible>T</visible>
      </menuitem>
      <menuitem>
        <id>SUBMITAS</id>
        <label>Save As</label>
        <visible>T</visible>
      </menuitem>
    </menu>
  </actionbar>
  <editingInList>T</editingInList>
</entryForm>
